skillkit/__init__.py
skillkit/py.typed
skillkit/core/__init__.py
skillkit/core/discovery.py
skillkit/core/exceptions.py
skillkit/core/manager.py
skillkit/core/models.py
skillkit/core/parser.py
skillkit/core/path_resolver.py
skillkit/core/processors.py
skillkit/integrations/__init__.py
skillkit/integrations/langchain.py
skillkit-0.2.0.dist-info/METADATA
skillkit-0.2.0.dist-info/WHEEL
skillkit-0.2.0.dist-info/licenses/LICENSE
skillkit-0.2.0.dist-info/RECORD
