Metadata-Version: 2.4
Name: skillkit
Version: 0.2.0
Summary: Python library implementing Anthropic's Agent Skills functionality for LLM-powered agents
Project-URL: Homepage, https://github.com/maxvaega/skillkit
Project-URL: Repository, https://github.com/maxvaega/skillkit
Project-URL: Documentation, https://github.com/maxvaega/skillkit#readme
Project-URL: Issues, https://github.com/maxvaega/skillkit/issues
Author-email: Massimo Olivieri <olivmassimo@gmail.com>
License: MIT
License-File: LICENSE
Keywords: agent-tools,agents,ai,anthropic,claude,langchain,llm,prompt-engineering,skills,tools
Classifier: Development Status :: 3 - Alpha
Classifier: Intended Audience :: Developers
Classifier: License :: OSI Approved :: MIT License
Classifier: Programming Language :: Python :: 3
Classifier: Programming Language :: Python :: 3.10
Classifier: Programming Language :: Python :: 3.11
Classifier: Programming Language :: Python :: 3.12
Classifier: Topic :: Scientific/Engineering :: Artificial Intelligence
Classifier: Topic :: Software Development :: Libraries :: Python Modules
Requires-Python: >=3.10
Requires-Dist: pyyaml>=6.0
Provides-Extra: all
Requires-Dist: langchain-core>=0.1.0; extra == 'all'
Requires-Dist: pydantic>=2.0; extra == 'all'
Provides-Extra: async
Provides-Extra: dev
Requires-Dist: mypy>=1.0; extra == 'dev'
Requires-Dist: pytest-asyncio>=0.21; extra == 'dev'
Requires-Dist: pytest-cov>=4.0; extra == 'dev'
Requires-Dist: pytest>=7.0; extra == 'dev'
Requires-Dist: ruff>=0.1.0; extra == 'dev'
Requires-Dist: types-pyyaml; extra == 'dev'
Provides-Extra: langchain
Requires-Dist: langchain-core>=0.1.0; extra == 'langchain'
Requires-Dist: pydantic>=2.0; extra == 'langchain'
